{
  "service": {
    "service": "hydrophone-local",
    "protocol": "http",
    "host": "localhost:9157",
    "keyFile": "config/key.pem",
    "certFile": "config/cert.pem"
  },
  "mongo": {
    "connectionString": "mongodb://localhost/hydrophone"
  },
  "hydrophone" : {
    "serverSecret": "This needs to be the same secret everywhere. YaHut75NsK1f9UKUXuWqxNN0RUwHFBCy",
    "emailTemplates" : {
      "passwordReset" : "{{define \"pwreset_test\"}} A test pw reset email  {{ .ToUser }} {{ .Key }} {{end}} {{template \"pwreset_test\" .}}",
      "careteamInvite" : "{{define \"invite_test\"}} A test careteam invite email  {{ .ToUser }} {{ .Key }} {{end}} {{template \"invite_test\" .}}",
      "confirmation" : "{{define \"confirm_test\"}} A test confirmation email  {{ .ToUser }} {{ .Key }} {{end}} {{template \"confirm_test\" .}}"
    }
  },
  "sesEmail" : {
    "serverEndpoint":"https://email.us-west-2.amazonaws.com",
    "fromAddress" : "noreply@tidepool.org",
    "accessKey": "AKIAJ6NEMHEY4CXV7LSQ",
    "secretKey": "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"
  }
}